uddsketch/__init__.py
uddsketch/_version.py
uddsketch/py.typed
uddsketch-0.2.0a2.dist-info/LICENSE
uddsketch-0.2.0a2.dist-info/METADATA
uddsketch-0.2.0a2.dist-info/WHEEL
uddsketch-0.2.0a2.dist-info/top_level.txt
uddsketch-0.2.0a2.dist-info/zip-safe
uddsketch-0.2.0a2.dist-info/RECORD
