Metadata-Version: 2.1
Name: uddsketch
Version: 0.2.0a2
Summary: uddsketch
Home-page: https://github.com/jettify/uddsketch-py
Download-URL: https://pypi.org/project/uddsketch/
Author: Nikolay Novik
Author-email: nickolainovik@gmail.com
License: Apache 2
Project-URL: Website, https://github.com/jettify/uddsketch
Project-URL: Documentation, https://uddsketch.readthedocs.io
Project-URL: Issues, https://github.com/jettify/uddsketch/issues
Keywords: uddsketch,ddsketch
Platform: POSIX
Classifier: License :: OSI Approved :: Apache Software License
Classifier: Intended Audience :: Developers
Classifier: Intended Audience :: Science/Research
Classifier: Programming Language :: Python :: 3
Classifier: Programming Language :: Python :: 3.8
Classifier: Programming Language :: Python :: 3.9
Classifier: Programming Language :: Python :: 3.10
Classifier: Programming Language :: Python :: 3.11
Classifier: Operating System :: OS Independent
Classifier: Development Status :: 3 - Alpha
Classifier: Topic :: Scientific/Engineering
Classifier: Topic :: Software Development :: Libraries
Requires-Python: >=3.7.0
License-File: LICENSE
